dbcode/__init__.py
dbcode/database.py
dbcode/utils.py
dbcode-0.1.dist-info/LICENSE
dbcode-0.1.dist-info/METADATA
dbcode-0.1.dist-info/WHEEL
dbcode-0.1.dist-info/top_level.txt
dbcode-0.1.dist-info/RECORD
