Metadata-Version: 2.1
Name: dbcode
Version: 0.1
Summary: dbcode
Home-page: UNKNOWN
Author: Vladimir N. Kalinin
Author-email: <vkalininz@mail.ru>
License: UNKNOWN
Keywords: python,database,sqlite3,postgresql,psycopg2
Platform: UNKNOWN
Classifier: Development Status :: 1 - Planning
Classifier: Intended Audience :: Developers
Classifier: Programming Language :: Python :: 3
Classifier: Operating System :: Microsoft :: Windows
License-File: LICENSE
Requires-Dist: psycopg2
Requires-Dist: psycopg2-binary
